cyares/callbacks.cpython-312-darwin.so
cyares/resulttypes.pxd
cyares/handles.pyx
cyares/aiohttp.py
cyares/socket_handle.c
cyares/exception.pxd
cyares/channel.pyi
cyares/callbacks.pyx
cyares/anyio.py
cyares/socket_handle.pyx
cyares/exception.c
cyares/__init__.pxd
cyares/exception.pyi
cyares/channel.pxd
cyares/__init__.py
cyares/resulttypes.c
cyares/socket_handle.cpython-312-darwin.so
cyares/resulttypes.pyi
cyares/handles.cpython-312-darwin.so
cyares/channel.c
cyares/handles.pyi
cyares/handles.c
cyares/trio.py
cyares/aio.py
cyares/channel.pyx
cyares/channel.cpython-312-darwin.so
cyares/py.typed
cyares/callbacks.pxd
cyares/exception.cpython-312-darwin.so
cyares/typedefs.py
cyares/socket_handle.pxd
cyares/resulttypes.cpython-312-darwin.so
cyares/deprecated_subclass.py
cyares/callbacks.c
cyares/exception.pyx
cyares/resulttypes.pyx
cyares/ares.pxd
cyares/handles.pxd
cyares/inc/__init__.pxd
cyares/inc/cares_flag_check.h
cyares/inc/cares_headers.h
cyares/inc/cyares_utils.h
cyares/inc/cyares_err_lookup.h
cyares-0.4.0.dist-info/RECORD
cyares-0.4.0.dist-info/WHEEL
cyares-0.4.0.dist-info/top_level.txt
cyares-0.4.0.dist-info/METADATA
cyares-0.4.0.dist-info/licenses/LICENSE
