Metadata-Version: 2.4
Name: cyares
Version: 0.4.0
Summary: A Cython Version of c-ares
Author-email: Vizonex <VizonexBusiness@gmail.com>
Project-URL: repository, https://github.com/Vizonex/cyares.git
Requires-Python: >=3.10
License-File: LICENSE
Requires-Dist: typing-extensions; python_version < "3.11"
Provides-Extra: aiohttp
Requires-Dist: aiohttp>=3.12.15; extra == "aiohttp"
Provides-Extra: all
Requires-Dist: idna>=2.1; extra == "all"
Requires-Dist: trio>=0.30.0; extra == "all"
Requires-Dist: aiohttp>=3.12.15; extra == "all"
Requires-Dist: anyio>=4.12.1; extra == "all"
Provides-Extra: idna
Requires-Dist: idna>=2.1; extra == "idna"
Provides-Extra: trio
Requires-Dist: trio>=0.30.0; extra == "trio"
Provides-Extra: anyio
Requires-Dist: anyio>=4.12.1; extra == "anyio"
Dynamic: license-file
